enerbitdso/VERSION
enerbitdso/__init__.py
enerbitdso/__main__.py
enerbitdso/cli.py
enerbitdso/config.py
enerbitdso/enerbit.py
enerbitdso/formats.py
enerbitdso/py.typed
enerbitdso/templates/DAY.xml.jinja2
enerbitdso/templates/INTERVAL.xml.jinja2
enerbitdso-0.1.20.dist-info/METADATA
enerbitdso-0.1.20.dist-info/WHEEL
enerbitdso-0.1.20.dist-info/entry_points.txt
enerbitdso-0.1.20.dist-info/licenses/LICENSE
enerbitdso-0.1.20.dist-info/RECORD
