Metadata-Version: 2.4
Name: enerbitdso
Version: 0.1.20
Summary: enerBit DSO (Distribution System Operator) API client
Author-email: CGM enerBit <operacion-fronteras@enerbit.co>
License: Copyright <2023> <ENERBIT SAS ESP>
License-File: LICENSE
Keywords: api,asic,client,colombia,distribution system operator,eneergia eléctrica,enerbit,energy,fronteras comerciales,mem,operador de red,potencia eléctrica,power,xm
Requires-Python: <3.11,>=3.10
Requires-Dist: httpx>=0.27.2
Requires-Dist: orjson>=3.10.10
Requires-Dist: pydantic-settings>=2.6.1
Requires-Dist: pydantic>=2.9.2
Requires-Dist: rich>=13.9.4
Requires-Dist: truststore>=0.10.0
Requires-Dist: typer>=0.12.5
Requires-Dist: tzdata>=2024.2
